cryptool/__init__.py
cryptool/exchanges/binance.py
cryptool-0.0.3.dist-info/LICENSE
cryptool-0.0.3.dist-info/WHEEL
cryptool-0.0.3.dist-info/METADATA
cryptool-0.0.3.dist-info/RECORD
