Metadata-Version: 2.1
Name: cryptool
Version: 0.0.3
Summary: cryptool is a python library to more easily deal with crypto exchanges
Home-page: https://github.com/carlok/cryptool
Author: Carlo Perassi
Author-email: carlo.perassi@gmail.com
Requires-Python: >=3.8
Classifier: License :: OSI Approved :: MIT License
Requires-Dist: pandas>=1.2.4
Requires-Dist: python-binance>=1.0.12
